{
  "schema_version": "pareto-web-v2",
  "summary": {
    "title": "H200 36 GPU Kimi-K2.6 C++ simulated EAGLE MTP Stage Pareto",
    "description": "36 GPU decode; MTP stage=0..9; accept rate=0.7; x-axis is TPS/user and y-axis is total throughput across all GPUs.",
    "point_count": 60,
    "frontier_count": 2,
    "x_metric": "tps_per_user",
    "y_metric": "throughput_total_tps",
    "pareto_rule": "for each fixed gpu_num, maximize TPS per user and total throughput across the strategy candidate set",
    "mtp_note": "MTP rows are generated by the native C++ cost model with MTP_on and mtp_stage enabled. Stage 0 is the matching baseline decode row.",
    "pp_note": "PP is swept when --pp-values includes values beyond 1. PD rows cap prefill at 20% of the fixed total, rounded down to an 8-GPU multiple, with decode taking the remainder. Decode A/F split rows pin the F side to groq-lpx3."
  },
  "point_columns": [
    "Config_Name",
    "hardware",
    "gpu_num",
    "strategy_type",
    "tpot_ns",
    "tpot_ms",
    "tps_per_user",
    "tps_per_gpu",
    "throughput_total_tps",
    "batch_attn_gpu",
    "batch_ffn_gpu",
    "total_machine_batch",
    "pp",
    "attn_dp",
    "attn_tp",
    "attn_cp",
    "ffn_ep",
    "ffn_tp",
    "mtp_stage",
    "mtp_model",
    "mtp_expected_tokens",
    "pd_enabled",
    "af_enabled",
    "prefill_gpu_num",
    "decode_gpu_num",
    "decode_ffn_gpu",
    "dominant_component",
    "MLA",
    "Load KV",
    "Dense MLP",
    "Dispatch time",
    "Shared Expert",
    "Routed expert",
    "Combine time",
    "final linear softmax",
    "MLA all reduce",
    "MLA cp ring",
    "FFN all reduce",
    "config_summary",
    "mode_summary",
    "decode_config_summary",
    "prefill_config_summary"
  ],
  "point_rows": [
    [
      "H200_36_decode_batch16_I400000_O32768",
      "HGX-H200",
      36,
      null,
      29615922.277419355,
      29.6159222774,
      34,
      136,
      4896,
      16,
      144,
      144,
      1,
      9,
      1,
      4,
      36,
      1,
      0,
      "simulated_baseline",
      1.0,
      null,
      null,
      null,
      null,
      null,
      "mla_compute",
      0.022395548,
      0.0010644697,
      8.3276e-05,
      0.0052545216,
      0.00055536,
      0.00333096,
      0.0004376256,
      0.000262737,
      0.0,
      0.0013378618,
      0.0,
      "attnGPU_b16 ffnGPU_b144 total_b144 g36 pp1 a(d/t/e/c)=9/1/1/4 f(d/t/e)=1/1/36 mtp_s0 decode36:attnGPU_b16",
      "MTP=off PD=off AF=off",
      "decode g=36 attnGPU_b=16 pp=1 attn dp/tp/ep/cp=9/1/1/4 ffn dp/tp/ep=1/1/36",
      "prefill off"
    ],
    [
      "H200_36_decode_batch16_I400000_O32768",
      "HGX-H200",
      36,
      null,
      31560516.67086198,
      31.5605166709,
      32,
      127,
      4572,
      16,
      144,
      144,
      1,
      9,
      1,
      4,
      18,
      2,
      0,
      "simulated_baseline",
      1.0,
      null,
      null,
      null,
      null,
      null,
      "mla_compute",
      0.022395548,
      0.0010644697,
      4.1654e-05,
      0.0052545216,
      0.0002778,
      0.0030534,
      0.0005752512,
      0.000262737,
      0.0,
      0.0013378618,
      0.001581506,
      "attnGPU_b16 ffnGPU_b144 total_b144 g36 pp1 a(d/t/e/c)=9/1/1/4 f(d/t/e)=1/2/18 mtp_s0 decode36:attnGPU_b16",
      "MTP=off PD=off AF=off",
      "decode g=36 attnGPU_b=16 pp=1 attn dp/tp/ep/cp=9/1/1/4 ffn dp/tp/ep=1/2/18",
      "prefill off"
    ],
    [
      "H200_36_decode_batch16_I400000_O32768",
      "HGX-H200",
      36,
      null,
      70188888.6,
      70.1888886,
      15,
      7,
      252,
      16,
      16,
      16,
      1,
      1,
      1,
      36,
      36,
      1,
      0,
      "simulated_baseline",
      1.0,
      null,
      null,
      null,
      null,
      null,
      "mla_cp_ring",
      0.003163281,
      0.0001183794,
      8.326e-05,
      0.0008505024,
      0.00055536,
      0.00610656,
      0.0003152917,
      0.000262733,
      0.0,
      0.0631809696,
      0.0,
      "attnGPU_b16 ffnGPU_b16 total_b16 g36 pp1 a(d/t/e/c)=1/1/1/36 f(d/t/e)=1/1/36 mtp_s0 decode36:attnGPU_b16",
      "MTP=off PD=off AF=off",
      "decode g=36 attnGPU_b=16 pp=1 attn dp/tp/ep/cp=1/1/1/36 ffn dp/tp/ep=1/1/36",
      "prefill off"
    ],
    [
      "H200_36_decode_batch16_I400000_O32768",
      "HGX-H200",
      36,
      null,
      69869706.6,
      69.8697066,
      15,
      7,
      252,
      16,
      16,
      16,
      1,
      1,
      1,
      36,
      18,
      2,
      0,
      "simulated_baseline",
      1.0,
      null,
      null,
      null,
      null,
      null,
      "mla_cp_ring",
      0.003163281,
      0.0001183794,
      4.1638e-05,
      0.0008505024,
      0.0002778,
      0.00610656,
      0.0003305835,
      0.000262733,
      0.0,
      0.0631809696,
      0.00146783,
      "attnGPU_b16 ffnGPU_b16 total_b16 g36 pp1 a(d/t/e/c)=1/1/1/36 f(d/t/e)=1/2/18 mtp_s0 decode36:attnGPU_b16",
      "MTP=off PD=off AF=off",
      "decode g=36 attnGPU_b=16 pp=1 attn dp/tp/ep/cp=1/1/1/36 ffn dp/tp/ep=1/2/18",
      "prefill off"
    ],
    [
      "H200_36_decode_batch16_I400000_O32768",
      "HGX-H200",
      36,
      null,
      21449283.48,
      21.44928348,
      47,
      83,
      2988,
      16,
      64,
      64,
      1,
      4,
      1,
      9,
      36,
      1,
      0,
      "simulated_baseline",
      1.0,
      null,
      null,
      null,
      null,
      null,
      "mla_cp_ring",
      0.010376104,
      0.0004732026,
      8.326e-05,
      0.0025020096,
      0.00055536,
      0.00610656,
      0.0003611669,
      0.000262733,
      0.0,
      0.0144413645,
      0.0,
      "attnGPU_b16 ffnGPU_b64 total_b64 g36 pp1 a(d/t/e/c)=4/1/1/9 f(d/t/e)=1/1/36 mtp_s0 decode36:attnGPU_b16",
      "MTP=off PD=off AF=off",
      "decode g=36 attnGPU_b=16 pp=1 attn dp/tp/ep/cp=4/1/1/9 ffn dp/tp/ep=1/1/36",
      "prefill off"
    ],
    [
      "H200_36_decode_batch16_I400000_O32768",
      "HGX-H200",
      36,
      null,
      21130101.48,
      21.13010148,
      48,
      85,
      3060,
      16,
      64,
      64,
      1,
      4,
      1,
      9,
      18,
      2,
      0,
      "simulated_baseline",
      1.0,
      null,
      null,
      null,
      null,
      null,
      "mla_cp_ring",
      0.010376104,
      0.0004732026,
      4.1638e-05,
      0.0025020096,
      0.0002778,
      0.00610656,
      0.0004223339,
      0.000262733,
      0.0,
      0.0144413645,
      0.001509798,
      "attnGPU_b16 ffnGPU_b64 total_b64 g36 pp1 a(d/t/e/c)=4/1/1/9 f(d/t/e)=1/2/18 mtp_s0 decode36:attnGPU_b16",
      "MTP=off PD=off AF=off",
      "decode g=36 attnGPU_b=16 pp=1 attn dp/tp/ep/cp=4/1/1/9 ffn dp/tp/ep=1/2/18",
      "prefill off"
    ],
    [
      "H200_36_decode_batch16_I400000_O32768",
      "HGX-H200",
      36,
      "mtp",
      56503492.87741935,
      56.5034928774,
      31,
      121,
      4356,
      16,
      144,
      144,
      1,
      9,
      1,
      4,
      36,
      1,
      1,
      "simulated",
      1.7,
      false,
      false,
      0.0,
      36.0,
      "",
      "mla_compute",
      0.044038704,
      0.0010644697,
      8.3308e-05,
      0.0102090432,
      0.0005556,
      0.00222096,
      0.0005752512,
      0.00027883,
      0.0,
      0.0015777235,
      0.0,
      "attnGPU_b16 ffnGPU_b144 total_b144 g36 pp1 a(d/t/e/c)=9/1/1/4 f(d/t/e)=1/1/36 mtp_s1 prefill=off decode36:attnGPU_b16",
      "MTP=on PD=off AF=off",
      "decode g=36 attnGPU_b=16 pp=1 attn dp/tp/ep/cp=9/1/1/4 ffn dp/tp/ep=1/1/36",
      "prefill off"
    ],
    [
      "H200_36_decode_batch16_I400000_O32768",
      "HGX-H200",
      36,
      "mtp",
      88887541.47741935,
      88.8875414774,
      25,
      99,
      3564,
      16,
      144,
      144,
      1,
      9,
      1,
      4,
      36,
      1,
      2,
      "simulated",
      2.19,
      false,
      false,
      0.0,
      36.0,
      "",
      "mla_compute",
      0.071094518,
      0.0010644697,
      9.5782e-05,
      0.0151635648,
      0.000624,
      0.00166608,
      0.0007128768,
      0.000298141,
      0.0,
      0.0018175853,
      0.0,
      "attnGPU_b16 ffnGPU_b144 total_b144 g36 pp1 a(d/t/e/c)=9/1/1/4 f(d/t/e)=1/1/36 mtp_s2 prefill=off decode36:attnGPU_b16",
      "MTP=on PD=off AF=off",
      "decode g=36 attnGPU_b=16 pp=1 attn dp/tp/ep/cp=9/1/1/4 ffn dp/tp/ep=1/1/36",
      "prefill off"
    ],
    [
      "H200_36_decode_batch16_I400000_O32768",
      "HGX-H200",
      36,
      "mtp",
      110559721.07741934,
      110.5597210774,
      23,
      92,
      3312,
      16,
      144,
      144,
      1,
      9,
      1,
      4,
      36,
      1,
      3,
      "simulated",
      2.533,
      false,
      false,
      0.0,
      36.0,
      "",
      "mla_compute",
      0.08733223,
      0.0010644697,
      0.000119104,
      0.0201180864,
      0.00079422,
      0.00114816,
      0.0008505024,
      0.000311017,
      0.0,
      0.002057447,
      0.0,
      "attnGPU_b16 ffnGPU_b144 total_b144 g36 pp1 a(d/t/e/c)=9/1/1/4 f(d/t/e)=1/1/36 mtp_s3 prefill=off decode36:attnGPU_b16",
      "MTP=on PD=off AF=off",
      "decode g=36 attnGPU_b=16 pp=1 attn dp/tp/ep/cp=9/1/1/4 ffn dp/tp/ep=1/1/36",
      "prefill off"
    ],
    [
      "H200_36_decode_batch16_I400000_O32768",
      "HGX-H200",
      36,
      "mtp",
      148558199.67741933,
      148.5581996774,
      19,
      75,
      2700,
      16,
      144,
      144,
      1,
      9,
      1,
      4,
      36,
      1,
      4,
      "simulated",
      2.7731,
      false,
      false,
      0.0,
      36.0,
      "",
      "mla_compute",
      0.119798742,
      0.0010644697,
      0.000159737,
      0.025072608,
      0.00103578,
      0.0011484,
      0.000988128,
      0.000332741,
      0.0,
      0.0022973088,
      0.0,
      "attnGPU_b16 ffnGPU_b144 total_b144 g36 pp1 a(d/t/e/c)=9/1/1/4 f(d/t/e)=1/1/36 mtp_s4 prefill=off decode36:attnGPU_b16",
      "MTP=on PD=off AF=off",
      "decode g=36 attnGPU_b=16 pp=1 attn dp/tp/ep/cp=9/1/1/4 ffn dp/tp/ep=1/1/36",
      "prefill off"
    ],
    [
      "H200_36_decode_batch16_I400000_O32768",
      "HGX-H200",
      36,
      "mtp",
      208197324.27741936,
      208.1973242774,
      15,
      57,
      2052,
      16,
      144,
      144,
      1,
      9,
      1,
      4,
      36,
      1,
      5,
      "simulated",
      2.94117,
      false,
      false,
      0.0,
      36.0,
      "",
      "mla_compute",
      0.173903654,
      0.0010644697,
      0.000177502,
      0.0300271296,
      0.00128154,
      0.0011556,
      0.0011257536,
      0.000375379,
      0.0,
      0.0025371706,
      0.0,
      "attnGPU_b16 ffnGPU_b144 total_b144 g36 pp1 a(d/t/e/c)=9/1/1/4 f(d/t/e)=1/1/36 mtp_s5 prefill=off decode36:attnGPU_b16",
      "MTP=on PD=off AF=off",
      "decode g=36 attnGPU_b=16 pp=1 attn dp/tp/ep/cp=9/1/1/4 ffn dp/tp/ep=1/1/36",
      "prefill off"
    ],
    [
      "H200_36_decode_batch16_I400000_O32768",
      "HGX-H200",
      36,
      "mtp",
      213736230.87741935,
      213.7362308774,
      15,
      58,
      2088,
      16,
      144,
      144,
      1,
      9,
      1,
      4,
      36,
      1,
      6,
      "simulated",
      3.058819,
      false,
      false,
      0.0,
      36.0,
      "",
      "mla_compute",
      0.173922753,
      0.0010644697,
      0.000212994,
      0.0349816512,
      0.0015378,
      0.00096234,
      0.0012633792,
      0.000375385,
      0.0,
      0.0027770323,
      0.0,
      "attnGPU_b16 ffnGPU_b144 total_b144 g36 pp1 a(d/t/e/c)=9/1/1/4 f(d/t/e)=1/1/36 mtp_s6 prefill=off decode36:attnGPU_b16",
      "MTP=on PD=off AF=off",
      "decode g=36 attnGPU_b=16 pp=1 attn dp/tp/ep/cp=9/1/1/4 ffn dp/tp/ep=1/1/36",
      "prefill off"
    ],
    [
      "H200_36_decode_batch16_I400000_O32768",
      "HGX-H200",
      36,
      "mtp",
      219433498.47741932,
      219.4334984774,
      15,
      58,
      2088,
      16,
      144,
      144,
      1,
      9,
      1,
      4,
      36,
      1,
      7,
      "simulated",
      3.1411733,
      false,
      false,
      0.0,
      36.0,
      "",
      "mla_compute",
      0.174100574,
      0.0010644697,
      0.000248485,
      0.0399361728,
      0.0017937,
      0.00096234,
      0.0014010048,
      0.000375391,
      0.0,
      0.0030168941,
      0.0,
      "attnGPU_b16 ffnGPU_b144 total_b144 g36 pp1 a(d/t/e/c)=9/1/1/4 f(d/t/e)=1/1/36 mtp_s7 prefill=off decode36:attnGPU_b16",
      "MTP=on PD=off AF=off",
      "decode g=36 attnGPU_b=16 pp=1 attn dp/tp/ep/cp=9/1/1/4 ffn dp/tp/ep=1/1/36",
      "prefill off"
    ],
    [
      "H200_36_decode_batch16_I400000_O32768",
      "HGX-H200",
      36,
      "mtp",
      398052469.07741934,
      398.0524690774,
      9,
      33,
      1188,
      16,
      144,
      144,
      1,
      9,
      1,
      4,
      36,
      1,
      8,
      "simulated",
      3.19882131,
      false,
      false,
      0.0,
      36.0,
      "",
      "mla_compute",
      0.347216686,
      0.0010644697,
      0.000266249,
      0.0448906944,
      0.00192204,
      0.00096666,
      0.0015386304,
      0.000504096,
      0.0,
      0.0032567558,
      0.0,
      "attnGPU_b16 ffnGPU_b144 total_b144 g36 pp1 a(d/t/e/c)=9/1/1/4 f(d/t/e)=1/1/36 mtp_s8 prefill=off decode36:attnGPU_b16",
      "MTP=on PD=off AF=off",
      "decode g=36 attnGPU_b=16 pp=1 attn dp/tp/ep/cp=9/1/1/4 ffn dp/tp/ep=1/1/36",
      "prefill off"
    ],
    [
      "H200_36_decode_batch16_I400000_O32768",
      "HGX-H200",
      36,
      "mtp",
      403688539.67741936,
      403.6885396774,
      9,
      33,
      1188,
      16,
      144,
      144,
      1,
      9,
      1,
      4,
      36,
      1,
      9,
      "simulated",
      3.239174917,
      false,
      false,
      0.0,
      36.0,
      "",
      "mla_compute",
      0.347319416,
      0.0010644697,
      0.000319474,
      0.049845216,
      0.0021741,
      0.0009669,
      0.001676256,
      0.000504102,
      0.0,
      0.0034966176,
      0.0,
      "attnGPU_b16 ffnGPU_b144 total_b144 g36 pp1 a(d/t/e/c)=9/1/1/4 f(d/t/e)=1/1/36 mtp_s9 prefill=off decode36:attnGPU_b16",
      "MTP=on PD=off AF=off",
      "decode g=36 attnGPU_b=16 pp=1 attn dp/tp/ep/cp=9/1/1/4 ffn dp/tp/ep=1/1/36",
      "prefill off"
    ],
    [
      "H200_36_decode_batch16_I400000_O32768",
      "HGX-H200",
      36,
      "mtp",
      58573697.76266526,
      58.5736977627,
      30,
      117,
      4212,
      16,
      144,
      144,
      1,
      9,
      1,
      4,
      18,
      2,
      1,
      "simulated",
      1.7,
      false,
      false,
      0.0,
      36.0,
      "",
      "mla_compute",
      0.044038704,
      0.0010644697,
      4.1686e-05,
      0.0102090432,
      0.00027804,
      0.00222096,
      0.0008505024,
      0.00027883,
      0.0,
      0.0015777235,
      0.00170921,
      "attnGPU_b16 ffnGPU_b144 total_b144 g36 pp1 a(d/t/e/c)=9/1/1/4 f(d/t/e)=1/2/18 mtp_s1 prefill=off decode36:attnGPU_b16",
      "MTP=on PD=off AF=off",
      "decode g=36 attnGPU_b=16 pp=1 attn dp/tp/ep/cp=9/1/1/4 ffn dp/tp/ep=1/2/18",
      "prefill off"
    ],
    [
      "H200_36_decode_batch16_I400000_O32768",
      "HGX-H200",
      36,
      "mtp",
      91051970.28069805,
      91.0519702807,
      25,
      97,
      3492,
      16,
      144,
      144,
      1,
      9,
      1,
      4,
      18,
      2,
      2,
      "simulated",
      2.19,
      false,
      false,
      0.0,
      36.0,
      "",
      "mla_compute",
      0.071094518,
      0.0010644697,
      4.7939e-05,
      0.0151635648,
      0.00031974,
      0.00140112,
      0.0011257536,
      0.000298141,
      0.0,
      0.0018175853,
      0.001838474,
      "attnGPU_b16 ffnGPU_b144 total_b144 g36 pp1 a(d/t/e/c)=9/1/1/4 f(d/t/e)=1/2/18 mtp_s2 prefill=off decode36:attnGPU_b16",
      "MTP=on PD=off AF=off",
      "decode g=36 attnGPU_b=16 pp=1 attn dp/tp/ep/cp=9/1/1/4 ffn dp/tp/ep=1/2/18",
      "prefill off"
    ],
    [
      "H200_36_decode_batch16_I400000_O32768",
      "HGX-H200",
      36,
      "mtp",
      112833913.37250131,
      112.8339133725,
      23,
      90,
      3240,
      16,
      144,
      144,
      1,
      9,
      1,
      4,
      18,
      2,
      3,
      "simulated",
      2.533,
      false,
      false,
      0.0,
      36.0,
      "",
      "mla_compute",
      0.08733223,
      0.0010644697,
      5.9614e-05,
      0.0201180864,
      0.00048576,
      0.00116088,
      0.0014010048,
      0.000311017,
      0.0,
      0.002057447,
      0.001966178,
      "attnGPU_b16 ffnGPU_b144 total_b144 g36 pp1 a(d/t/e/c)=9/1/1/4 f(d/t/e)=1/2/18 mtp_s3 prefill=off decode36:attnGPU_b16",
      "MTP=on PD=off AF=off",
      "decode g=36 attnGPU_b=16 pp=1 attn dp/tp/ep/cp=9/1/1/4 ffn dp/tp/ep=1/2/18",
      "prefill off"
    ],
    [
      "H200_36_decode_batch16_I400000_O32768",
      "HGX-H200",
      36,
      "mtp",
      150731937.8905341,
      150.7319378905,
      19,
      74,
      2664,
      16,
      144,
      144,
      1,
      9,
      1,
      4,
      18,
      2,
      4,
      "simulated",
      2.7731,
      false,
      false,
      0.0,
      36.0,
      "",
      "mla_compute",
      0.119798742,
      0.0010644697,
      7.9948e-05,
      0.025072608,
      0.00052002,
      0.00106608,
      0.001676256,
      0.000332741,
      0.0,
      0.0022973088,
      0.002095442,
      "attnGPU_b16 ffnGPU_b144 total_b144 g36 pp1 a(d/t/e/c)=9/1/1/4 f(d/t/e)=1/2/18 mtp_s4 prefill=off decode36:attnGPU_b16",
      "MTP=on PD=off AF=off",
      "decode g=36 attnGPU_b=16 pp=1 attn dp/tp/ep/cp=9/1/1/4 ffn dp/tp/ep=1/2/18",
      "prefill off"
    ],
    [
      "H200_36_decode_batch16_I400000_O32768",
      "HGX-H200",
      36,
      "mtp",
      210363725.9823374,
      210.3637259823,
      14,
      56,
      2016,
      16,
      144,
      144,
      1,
      9,
      1,
      4,
      18,
      2,
      5,
      "simulated",
      2.94117,
      false,
      false,
      0.0,
      36.0,
      "",
      "mla_compute",
      0.173903654,
      0.0010644697,
      8.8846e-05,
      0.0300271296,
      0.00064158,
      0.00106992,
      0.0019515072,
      0.000375379,
      0.0,
      0.0025371706,
      0.002223268,
      "attnGPU_b16 ffnGPU_b144 total_b144 g36 pp1 a(d/t/e/c)=9/1/1/4 f(d/t/e)=1/2/18 mtp_s5 prefill=off decode36:attnGPU_b16",
      "MTP=on PD=off AF=off",
      "decode g=36 attnGPU_b=16 pp=1 attn dp/tp/ep/cp=9/1/1/4 ffn dp/tp/ep=1/2/18",
      "prefill off"
    ],
    [
      "H200_36_decode_batch16_I400000_O32768",
      "HGX-H200",
      36,
      "mtp",
      215883947.50037017,
      215.8839475004,
      15,
      57,
      2052,
      16,
      144,
      144,
      1,
      9,
      1,
      4,
      18,
      2,
      6,
      "simulated",
      3.058819,
      false,
      false,
      0.0,
      36.0,
      "",
      "mla_compute",
      0.173922753,
      0.0010644697,
      0.000106608,
      0.0349816512,
      0.00076974,
      0.00097116,
      0.0022267584,
      0.000375385,
      0.0,
      0.0027770323,
      0.002352532,
      "attnGPU_b16 ffnGPU_b144 total_b144 g36 pp1 a(d/t/e/c)=9/1/1/4 f(d/t/e)=1/2/18 mtp_s6 prefill=off decode36:attnGPU_b16",
      "MTP=on PD=off AF=off",
      "decode g=36 attnGPU_b=16 pp=1 attn dp/tp/ep/cp=9/1/1/4 ffn dp/tp/ep=1/2/18",
      "prefill off"
    ],
    [
      "H200_36_decode_batch16_I400000_O32768",
      "HGX-H200",
      36,
      "mtp",
      221561173.59217343,
      221.5611735922,
      15,
      57,
      2052,
      16,
      144,
      144,
      1,
      9,
      1,
      4,
      18,
      2,
      7,
      "simulated",
      3.1411733,
      false,
      false,
      0.0,
      36.0,
      "",
      "mla_compute",
      0.174100574,
      0.0010644697,
      0.000124367,
      0.0399361728,
      0.00089772,
      0.00097116,
      0.0025020096,
      0.000375391,
      0.0,
      0.0030168941,
      0.002480236,
      "attnGPU_b16 ffnGPU_b144 total_b144 g36 pp1 a(d/t/e/c)=9/1/1/4 f(d/t/e)=1/2/18 mtp_s7 prefill=off decode36:attnGPU_b16",
      "MTP=on PD=off AF=off",
      "decode g=36 attnGPU_b=16 pp=1 attn dp/tp/ep/cp=9/1/1/4 ffn dp/tp/ep=1/2/18",
      "prefill off"
    ],
    [
      "H200_36_decode_batch16_I400000_O32768",
      "HGX-H200",
      36,
      "mtp",
      400234403.1102063,
      400.2344031102,
      8,
      32,
      1152,
      16,
      144,
      144,
      1,
      9,
      1,
      4,
      18,
      2,
      8,
      "simulated",
      3.19882131,
      false,
      false,
      0.0,
      36.0,
      "",
      "mla_compute",
      0.347216686,
      0.0010644697,
      0.000133265,
      0.0448906944,
      0.00096204,
      0.00097668,
      0.0027772608,
      0.000504096,
      0.0,
      0.0032567558,
      0.0026095,
      "attnGPU_b16 ffnGPU_b144 total_b144 g36 pp1 a(d/t/e/c)=9/1/1/4 f(d/t/e)=1/2/18 mtp_s8 prefill=off decode36:attnGPU_b16",
      "MTP=on PD=off AF=off",
      "decode g=36 attnGPU_b=16 pp=1 attn dp/tp/ep/cp=9/1/1/4 ffn dp/tp/ep=1/2/18",
      "prefill off"
    ],
    [
      "H200_36_decode_batch16_I400000_O32768",
      "HGX-H200",
      36,
      "mtp",
      405865567.2020096,
      405.865567202,
      8,
      32,
      1152,
      16,
      144,
      144,
      1,
      9,
      1,
      4,
      18,
      2,
      9,
      "simulated",
      3.239174917,
      false,
      false,
      0.0,
      36.0,
      "",
      "mla_compute",
      0.347319416,
      0.0010644697,
      0.000159893,
      0.049845216,
      0.00111018,
      0.00097692,
      0.003052512,
      0.000504102,
      0.0,
      0.0034966176,
      0.002737204,
      "attnGPU_b16 ffnGPU_b144 total_b144 g36 pp1 a(d/t/e/c)=9/1/1/4 f(d/t/e)=1/2/18 mtp_s9 prefill=off decode36:attnGPU_b16",
      "MTP=on PD=off AF=off",
      "decode g=36 attnGPU_b=16 pp=1 attn dp/tp/ep/cp=9/1/1/4 ffn dp/tp/ep=1/2/18",
      "prefill off"
    ],
    [
      "H200_36_decode_batch16_I400000_O32768",
      "HGX-H200",
      36,
      "mtp",
      120849467.2,
      120.8494672,
      15,
      7,
      252,
      16,
      16,
      16,
      1,
      1,
      1,
      36,
      36,
      1,
      1,
      "simulated",
      1.7,
      false,
      false,
      0.0,
      36.0,
      "",
      "mla_cp_ring",
      0.005574084,
      0.0001183794,
      8.326e-05,
      0.0014010048,
      0.00055536,
      0.00610656,
      0.0003305835,
      0.00027882,
      0.0,
      0.1135519392,
      0.0,
      "attnGPU_b16 ffnGPU_b16 total_b16 g36 pp1 a(d/t/e/c)=1/1/1/36 f(d/t/e)=1/1/36 mtp_s1 prefill=off decode36:attnGPU_b16",
      "MTP=on PD=off AF=off",
      "decode g=36 attnGPU_b=16 pp=1 attn dp/tp/ep/cp=1/1/1/36 ffn dp/tp/ep=1/1/36",
      "prefill off"
    ],
    [
      "H200_36_decode_batch16_I400000_O32768",
      "HGX-H200",
      36,
      "mtp",
      171513263.80000004,
      171.5132638,
      13,
      6,
      216,
      16,
      16,
      16,
      1,
      1,
      1,
      36,
      36,
      1,
      2,
      "simulated",
      2.19,
      false,
      false,
      0.0,
      36.0,
      "",
      "mla_cp_ring",
      0.008589526,
      0.0001183794,
      8.326e-05,
      0.0019515072,
      0.00055536,
      0.00610656,
      0.0003458752,
      0.000298125,
      0.0,
      0.1639229088,
      0.0,
      "attnGPU_b16 ffnGPU_b16 total_b16 g36 pp1 a(d/t/e/c)=1/1/1/36 f(d/t/e)=1/1/36 mtp_s2 prefill=off decode36:attnGPU_b16",
      "MTP=on PD=off AF=off",
      "decode g=36 attnGPU_b=16 pp=1 attn dp/tp/ep/cp=1/1/1/36 ffn dp/tp/ep=1/1/36",
      "prefill off"
    ],
    [
      "H200_36_decode_batch16_I400000_O32768",
      "HGX-H200",
      36,
      "mtp",
      222170625.4,
      222.1706254,
      12,
      6,
      216,
      16,
      16,
      16,
      1,
      1,
      1,
      36,
      36,
      1,
      3,
      "simulated",
      2.533,
      false,
      false,
      0.0,
      36.0,
      "",
      "mla_cp_ring",
      0.010402866,
      0.0001183794,
      8.326e-05,
      0.0025020096,
      0.00055536,
      0.00610656,
      0.0003611669,
      0.000310995,
      0.0,
      0.2142938784,
      0.0,
      "attnGPU_b16 ffnGPU_b16 total_b16 g36 pp1 a(d/t/e/c)=1/1/1/36 f(d/t/e)=1/1/36 mtp_s3 prefill=off decode36:attnGPU_b16",
      "MTP=on PD=off AF=off",
      "decode g=36 attnGPU_b=16 pp=1 attn dp/tp/ep/cp=1/1/1/36 ffn dp/tp/ep=1/1/36",
      "prefill off"
    ],
    [
      "H200_36_decode_batch16_I400000_O32768",
      "HGX-H200",
      36,
      "mtp",
      272836859.0,
      272.836859,
      11,
      5,
      180,
      16,
      16,
      16,
      1,
      1,
      1,
      36,
      36,
      1,
      4,
      "simulated",
      2.7731,
      false,
      false,
      0.0,
      36.0,
      "",
      "mla_cp_ring",
      0.014021254,
      0.0001183794,
      8.3276e-05,
      0.003052512,
      0.00055536,
      0.00610656,
      0.0003764587,
      0.000332717,
      0.0,
      0.264664848,
      0.0,
      "attnGPU_b16 ffnGPU_b16 total_b16 g36 pp1 a(d/t/e/c)=1/1/1/36 f(d/t/e)=1/1/36 mtp_s4 prefill=off decode36:attnGPU_b16",
      "MTP=on PD=off AF=off",
      "decode g=36 attnGPU_b=16 pp=1 attn dp/tp/ep/cp=1/1/1/36 ffn dp/tp/ep=1/1/36",
      "prefill off"
    ],
    [
      "H200_36_decode_batch16_I400000_O32768",
      "HGX-H200",
      36,
      "mtp",
      323523982.6000001,
      323.5239826,
      10,
      5,
      180,
      16,
      16,
      16,
      1,
      1,
      1,
      36,
      36,
      1,
      5,
      "simulated",
      2.94117,
      false,
      false,
      0.0,
      36.0,
      "",
      "mla_cp_ring",
      0.020045794,
      0.0001183794,
      8.3276e-05,
      0.0036030144,
      0.00055536,
      0.00610656,
      0.0003917504,
      0.000375349,
      0.0,
      0.3150358176,
      0.0,
      "attnGPU_b16 ffnGPU_b16 total_b16 g36 pp1 a(d/t/e/c)=1/1/1/36 f(d/t/e)=1/1/36 mtp_s5 prefill=off decode36:attnGPU_b16",
      "MTP=on PD=off AF=off",
      "decode g=36 attnGPU_b=16 pp=1 attn dp/tp/ep/cp=1/1/1/36 ffn dp/tp/ep=1/1/36",
      "prefill off"
    ],
    [
      "H200_36_decode_batch16_I400000_O32768",
      "HGX-H200",
      36,
      "mtp",
      372215430.99999994,
      372.215431,
      9,
      4,
      144,
      16,
      16,
      16,
      1,
      1,
      1,
      36,
      36,
      1,
      6,
      "simulated",
      3.058819,
      false,
      false,
      0.0,
      36.0,
      "",
      "mla_cp_ring",
      0.020064521,
      0.0001183794,
      8.3276e-05,
      0.0041535168,
      0.00055536,
      0.00333096,
      0.0004070421,
      0.000375349,
      0.0,
      0.3654067872,
      0.0,
      "attnGPU_b16 ffnGPU_b16 total_b16 g36 pp1 a(d/t/e/c)=1/1/1/36 f(d/t/e)=1/1/36 mtp_s6 prefill=off decode36:attnGPU_b16",
      "MTP=on PD=off AF=off",
      "decode g=36 attnGPU_b=16 pp=1 attn dp/tp/ep/cp=1/1/1/36 ffn dp/tp/ep=1/1/36",
      "prefill off"
    ],
    [
      "H200_36_decode_batch16_I400000_O32768",
      "HGX-H200",
      36,
      "mtp",
      423410425.0,
      423.410425,
      8,
      4,
      144,
      16,
      16,
      16,
      1,
      1,
      1,
      36,
      36,
      1,
      7,
      "simulated",
      3.1411733,
      false,
      false,
      0.0,
      36.0,
      "",
      "mla_cp_ring",
      0.02024197,
      0.0001183794,
      8.3276e-05,
      0.0047040192,
      0.00055536,
      0.00333096,
      0.0004223339,
      0.000375349,
      0.0,
      0.4157777568,
      0.0,
      "attnGPU_b16 ffnGPU_b16 total_b16 g36 pp1 a(d/t/e/c)=1/1/1/36 f(d/t/e)=1/1/36 mtp_s7 prefill=off decode36:attnGPU_b16",
      "MTP=on PD=off AF=off",
      "decode g=36 attnGPU_b=16 pp=1 attn dp/tp/ep/cp=1/1/1/36 ffn dp/tp/ep=1/1/36",
      "prefill off"
    ],
    [
      "H200_36_decode_batch16_I400000_O32768",
      "HGX-H200",
      36,
      "mtp",
      474734117.99999994,
      474.734118,
      7,
      3,
      108,
      16,
      16,
      16,
      1,
      1,
      1,
      36,
      36,
      1,
      8,
      "simulated",
      3.19882131,
      false,
      false,
      0.0,
      36.0,
      "",
      "mla_cp_ring",
      0.03950171,
      0.0001183794,
      8.3276e-05,
      0.0052545216,
      0.00055536,
      0.00333096,
      0.0004376256,
      0.000504048,
      0.0,
      0.4661487264,
      0.0,
      "attnGPU_b16 ffnGPU_b16 total_b16 g36 pp1 a(d/t/e/c)=1/1/1/36 f(d/t/e)=1/1/36 mtp_s8 prefill=off decode36:attnGPU_b16",
      "MTP=on PD=off AF=off",
      "decode g=36 attnGPU_b=16 pp=1 attn dp/tp/ep/cp=1/1/1/36 ffn dp/tp/ep=1/1/36",
      "prefill off"
    ],
    [
      "H200_36_decode_batch16_I400000_O32768",
      "HGX-H200",
      36,
      "mtp",
      525929372.0,
      525.929372,
      7,
      3,
      108,
      16,
      16,
      16,
      1,
      1,
      1,
      36,
      36,
      1,
      9,
      "simulated",
      3.239174917,
      false,
      false,
      0.0,
      36.0,
      "",
      "mla_cp_ring",
      0.039604192,
      0.0001183794,
      8.3292e-05,
      0.005805024,
      0.0005556,
      0.0033312,
      0.0004529173,
      0.00050405,
      0.0,
      0.516519696,
      0.0,
      "attnGPU_b16 ffnGPU_b16 total_b16 g36 pp1 a(d/t/e/c)=1/1/1/36 f(d/t/e)=1/1/36 mtp_s9 prefill=off decode36:attnGPU_b16",
      "MTP=on PD=off AF=off",
      "decode g=36 attnGPU_b=16 pp=1 attn dp/tp/ep/cp=1/1/1/36 ffn dp/tp/ep=1/1/36",
      "prefill off"
    ],
    [
      "H200_36_decode_batch16_I400000_O32768",
      "HGX-H200",
      36,
      "mtp",
      120530285.2,
      120.5302852,
      15,
      7,
      252,
      16,
      16,
      16,
      1,
      1,
      1,
      36,
      18,
      2,
      1,
      "simulated",
      1.7,
      false,
      false,
      0.0,
      36.0,
      "",
      "mla_cp_ring",
      0.005574084,
      0.0001183794,
      4.1638e-05,
      0.0014010048,
      0.0002778,
      0.00610656,
      0.0003611669,
      0.00027882,
      0.0,
      0.1135519392,
      0.00148186,
      "attnGPU_b16 ffnGPU_b16 total_b16 g36 pp1 a(d/t/e/c)=1/1/1/36 f(d/t/e)=1/2/18 mtp_s1 prefill=off decode36:attnGPU_b16",
      "MTP=on PD=off AF=off",
      "decode g=36 attnGPU_b=16 pp=1 attn dp/tp/ep/cp=1/1/1/36 ffn dp/tp/ep=1/2/18",
      "prefill off"
    ],
    [
      "H200_36_decode_batch16_I400000_O32768",
      "HGX-H200",
      36,
      "mtp",
      171194081.80000004,
      171.1940818,
      13,
      6,
      216,
      16,
      16,
      16,
      1,
      1,
      1,
      36,
      18,
      2,
      2,
      "simulated",
      2.19,
      false,
      false,
      0.0,
      36.0,
      "",
      "mla_cp_ring",
      0.008589526,
      0.0001183794,
      4.1638e-05,
      0.0019515072,
      0.0002778,
      0.00610656,
      0.0003917504,
      0.000298125,
      0.0,
      0.1639229088,
      0.00149589,
      "attnGPU_b16 ffnGPU_b16 total_b16 g36 pp1 a(d/t/e/c)=1/1/1/36 f(d/t/e)=1/2/18 mtp_s2 prefill=off decode36:attnGPU_b16",
      "MTP=on PD=off AF=off",
      "decode g=36 attnGPU_b=16 pp=1 attn dp/tp/ep/cp=1/1/1/36 ffn dp/tp/ep=1/2/18",
      "prefill off"
    ],
    [
      "H200_36_decode_batch16_I400000_O32768",
      "HGX-H200",
      36,
      "mtp",
      221851443.4,
      221.8514434,
      12,
      6,
      216,
      16,
      16,
      16,
      1,
      1,
      1,
      36,
      18,
      2,
      3,
      "simulated",
      2.533,
      false,
      false,
      0.0,
      36.0,
      "",
      "mla_cp_ring",
      0.010402866,
      0.0001183794,
      4.1638e-05,
      0.0025020096,
      0.0002778,
      0.00610656,
      0.0004223339,
      0.000310995,
      0.0,
      0.2142938784,
      0.001509798,
      "attnGPU_b16 ffnGPU_b16 total_b16 g36 pp1 a(d/t/e/c)=1/1/1/36 f(d/t/e)=1/2/18 mtp_s3 prefill=off decode36:attnGPU_b16",
      "MTP=on PD=off AF=off",
      "decode g=36 attnGPU_b=16 pp=1 attn dp/tp/ep/cp=1/1/1/36 ffn dp/tp/ep=1/2/18",
      "prefill off"
    ],
    [
      "H200_36_decode_batch16_I400000_O32768",
      "HGX-H200",
      36,
      "mtp",
      272517677.0,
      272.517677,
      11,
      5,
      180,
      16,
      16,
      16,
      1,
      1,
      1,
      36,
      18,
      2,
      4,
      "simulated",
      2.7731,
      false,
      false,
      0.0,
      36.0,
      "",
      "mla_cp_ring",
      0.014021254,
      0.0001183794,
      4.1654e-05,
      0.003052512,
      0.0002778,
      0.00610656,
      0.0004529173,
      0.000332717,
      0.0,
      0.264664848,
      0.001523828,
      "attnGPU_b16 ffnGPU_b16 total_b16 g36 pp1 a(d/t/e/c)=1/1/1/36 f(d/t/e)=1/2/18 mtp_s4 prefill=off decode36:attnGPU_b16",
      "MTP=on PD=off AF=off",
      "decode g=36 attnGPU_b=16 pp=1 attn dp/tp/ep/cp=1/1/1/36 ffn dp/tp/ep=1/2/18",
      "prefill off"
    ],
    [
      "H200_36_decode_batch16_I400000_O32768",
      "HGX-H200",
      36,
      "mtp",
      323204800.6000001,
      323.2048006,
      10,
      5,
      180,
      16,
      16,
      16,
      1,
      1,
      1,
      36,
      18,
      2,
      5,
      "simulated",
      2.94117,
      false,
      false,
      0.0,
      36.0,
      "",
      "mla_cp_ring",
      0.020045794,
      0.0001183794,
      4.1654e-05,
      0.0036030144,
      0.0002778,
      0.00610656,
      0.0004835008,
      0.000375349,
      0.0,
      0.3150358176,
      0.001537858,
      "attnGPU_b16 ffnGPU_b16 total_b16 g36 pp1 a(d/t/e/c)=1/1/1/36 f(d/t/e)=1/2/18 mtp_s5 prefill=off decode36:attnGPU_b16",
      "MTP=on PD=off AF=off",
      "decode g=36 attnGPU_b=16 pp=1 attn dp/tp/ep/cp=1/1/1/36 ffn dp/tp/ep=1/2/18",
      "prefill off"
    ],
    [
      "H200_36_decode_batch16_I400000_O32768",
      "HGX-H200",
      36,
      "mtp",
      374132425.3934426,
      374.1324253934,
      9,
      4,
      144,
      16,
      16,
      16,
      1,
      1,
      1,
      36,
      18,
      2,
      6,
      "simulated",
      3.058819,
      false,
      false,
      0.0,
      36.0,
      "",
      "mla_cp_ring",
      0.020064521,
      0.0001183794,
      4.1654e-05,
      0.0041535168,
      0.0002778,
      0.0030534,
      0.0005140843,
      0.000375349,
      0.0,
      0.3654067872,
      0.001553446,
      "attnGPU_b16 ffnGPU_b16 total_b16 g36 pp1 a(d/t/e/c)=1/1/1/36 f(d/t/e)=1/2/18 mtp_s6 prefill=off decode36:attnGPU_b16",
      "MTP=on PD=off AF=off",
      "decode g=36 attnGPU_b=16 pp=1 attn dp/tp/ep/cp=1/1/1/36 ffn dp/tp/ep=1/2/18",
      "prefill off"
    ],
    [
      "H200_36_decode_batch16_I400000_O32768",
      "HGX-H200",
      36,
      "mtp",
      425341219.39344263,
      425.3412193934,
      8,
      4,
      144,
      16,
      16,
      16,
      1,
      1,
      1,
      36,
      18,
      2,
      7,
      "simulated",
      3.1411733,
      false,
      false,
      0.0,
      36.0,
      "",
      "mla_cp_ring",
      0.02024197,
      0.0001183794,
      4.1654e-05,
      0.0047040192,
      0.0002778,
      0.0030534,
      0.0005446677,
      0.000375349,
      0.0,
      0.4157777568,
      0.001567476,
      "attnGPU_b16 ffnGPU_b16 total_b16 g36 pp1 a(d/t/e/c)=1/1/1/36 f(d/t/e)=1/2/18 mtp_s7 prefill=off decode36:attnGPU_b16",
      "MTP=on PD=off AF=off",
      "decode g=36 attnGPU_b=16 pp=1 attn dp/tp/ep/cp=1/1/1/36 ffn dp/tp/ep=1/2/18",
      "prefill off"
    ],
    [
      "H200_36_decode_batch16_I400000_O32768",
      "HGX-H200",
      36,
      "mtp",
      476678712.3934426,
      476.6787123934,
      7,
      3,
      108,
      16,
      16,
      16,
      1,
      1,
      1,
      36,
      18,
      2,
      8,
      "simulated",
      3.19882131,
      false,
      false,
      0.0,
      36.0,
      "",
      "mla_cp_ring",
      0.03950171,
      0.0001183794,
      4.1654e-05,
      0.0052545216,
      0.0002778,
      0.0030534,
      0.0005752512,
      0.000504048,
      0.0,
      0.4661487264,
      0.001581506,
      "attnGPU_b16 ffnGPU_b16 total_b16 g36 pp1 a(d/t/e/c)=1/1/1/36 f(d/t/e)=1/2/18 mtp_s8 prefill=off decode36:attnGPU_b16",
      "MTP=on PD=off AF=off",
      "decode g=36 attnGPU_b=16 pp=1 attn dp/tp/ep/cp=1/1/1/36 ffn dp/tp/ep=1/2/18",
      "prefill off"
    ],
    [
      "H200_36_decode_batch16_I400000_O32768",
      "HGX-H200",
      36,
      "mtp",
      527887646.39344263,
      527.8876463934,
      7,
      3,
      108,
      16,
      16,
      16,
      1,
      1,
      1,
      36,
      18,
      2,
      9,
      "simulated",
      3.239174917,
      false,
      false,
      0.0,
      36.0,
      "",
      "mla_cp_ring",
      0.039604192,
      0.0001183794,
      4.167e-05,
      0.005805024,
      0.00027804,
      0.00305364,
      0.0006058347,
      0.00050405,
      0.0,
      0.516519696,
      0.001595414,
      "attnGPU_b16 ffnGPU_b16 total_b16 g36 pp1 a(d/t/e/c)=1/1/1/36 f(d/t/e)=1/2/18 mtp_s9 prefill=off decode36:attnGPU_b16",
      "MTP=on PD=off AF=off",
      "decode g=36 attnGPU_b=16 pp=1 attn dp/tp/ep/cp=1/1/1/36 ffn dp/tp/ep=1/2/18",
      "prefill off"
    ],
    [
      "H200_36_decode_batch16_I400000_O32768",
      "HGX-H200",
      36,
      "mtp",
      31849740.16,
      31.84974016,
      54,
      95,
      3420,
      16,
      64,
      64,
      1,
      4,
      1,
      9,
      36,
      1,
      1,
      "simulated",
      1.7,
      false,
      false,
      0.0,
      36.0,
      "",
      "mla_cp_ring",
      0.019999932,
      0.0004732026,
      8.3276e-05,
      0.0047040192,
      0.00055536,
      0.00333096,
      0.0004223339,
      0.000278824,
      0.0,
      0.025954729,
      0.0,
      "attnGPU_b16 ffnGPU_b64 total_b64 g36 pp1 a(d/t/e/c)=4/1/1/9 f(d/t/e)=1/1/36 mtp_s1 prefill=off decode36:attnGPU_b16",
      "MTP=on PD=off AF=off",
      "decode g=36 attnGPU_b=16 pp=1 attn dp/tp/ep/cp=4/1/1/9 ffn dp/tp/ep=1/1/36",
      "prefill off"
    ],
    [
      "H200_36_decode_batch16_I400000_O32768",
      "HGX-H200",
      36,
      "mtp",
      45858201.24,
      45.85820124,
      48,
      85,
      3060,
      16,
      64,
      64,
      1,
      4,
      1,
      9,
      36,
      1,
      2,
      "simulated",
      2.19,
      false,
      false,
      0.0,
      36.0,
      "",
      "mla_cp_ring",
      0.032031498,
      0.0004732026,
      8.3292e-05,
      0.0069060288,
      0.0005556,
      0.0033312,
      0.0004835008,
      0.000298131,
      0.0,
      0.0374680934,
      0.0,
      "attnGPU_b16 ffnGPU_b64 total_b64 g36 pp1 a(d/t/e/c)=4/1/1/9 f(d/t/e)=1/1/36 mtp_s2 prefill=off decode36:attnGPU_b16",
      "MTP=on PD=off AF=off",
      "decode g=36 attnGPU_b=16 pp=1 attn dp/tp/ep/cp=4/1/1/9 ffn dp/tp/ep=1/1/36",
      "prefill off"
    ],
    [
      "H200_36_decode_batch16_I400000_O32768",
      "HGX-H200",
      36,
      "mtp",
      59859991.32,
      59.85999132,
      43,
      76,
      2736,
      16,
      64,
      64,
      1,
      4,
      1,
      9,
      36,
      1,
      3,
      "simulated",
      2.533,
      false,
      false,
      0.0,
      36.0,
      "",
      "mla_cp_ring",
      0.039254686,
      0.0004732026,
      8.3308e-05,
      0.0091080384,
      0.0005556,
      0.00222096,
      0.0005446677,
      0.000311005,
      0.0,
      0.0489814579,
      0.0,
      "attnGPU_b16 ffnGPU_b64 total_b64 g36 pp1 a(d/t/e/c)=4/1/1/9 f(d/t/e)=1/1/36 mtp_s3 prefill=off decode36:attnGPU_b16",
      "MTP=on PD=off AF=off",
      "decode g=36 attnGPU_b=16 pp=1 attn dp/tp/ep/cp=4/1/1/9 ffn dp/tp/ep=1/1/36",
      "prefill off"
    ],
    [
      "H200_36_decode_batch16_I400000_O32768",
      "HGX-H200",
      36,
      "mtp",
      73870865.4,
      73.8708654,
      38,
      67,
      2412,
      16,
      64,
      64,
      1,
      4,
      1,
      9,
      36,
      1,
      4,
      "simulated",
      2.7731,
      false,
      false,
      0.0,
      36.0,
      "",
      "mla_cp_ring",
      0.05369215,
      0.0004732026,
      8.3324e-05,
      0.011310048,
      0.00055584,
      0.00166608,
      0.0006058347,
      0.000332725,
      0.0,
      0.0604948224,
      0.0,
      "attnGPU_b16 ffnGPU_b64 total_b64 g36 pp1 a(d/t/e/c)=4/1/1/9 f(d/t/e)=1/1/36 mtp_s4 prefill=off decode36:attnGPU_b16",
      "MTP=on PD=off AF=off",
      "decode g=36 attnGPU_b=16 pp=1 attn dp/tp/ep/cp=4/1/1/9 ffn dp/tp/ep=1/1/36",
      "prefill off"
    ],
    [
      "H200_36_decode_batch16_I400000_O32768",
      "HGX-H200",
      36,
      "mtp",
      94116371.18064515,
      94.1163711806,
      32,
      56,
      2016,
      16,
      64,
      64,
      1,
      4,
      1,
      9,
      36,
      1,
      5,
      "simulated",
      2.94117,
      false,
      false,
      0.0,
      36.0,
      "",
      "mla_compute",
      0.077748938,
      0.0004732026,
      8.334e-05,
      0.0135120576,
      0.00055584,
      0.00166608,
      0.0006670016,
      0.000375361,
      0.0,
      0.0720081869,
      0.0,
      "attnGPU_b16 ffnGPU_b64 total_b64 g36 pp1 a(d/t/e/c)=4/1/1/9 f(d/t/e)=1/1/36 mtp_s5 prefill=off decode36:attnGPU_b16",
      "MTP=on PD=off AF=off",
      "decode g=36 attnGPU_b=16 pp=1 attn dp/tp/ep/cp=4/1/1/9 ffn dp/tp/ep=1/1/36",
      "prefill off"
    ],
    [
      "H200_36_decode_batch16_I400000_O32768",
      "HGX-H200",
      36,
      "mtp",
      102012111.56,
      102.01211156,
      30,
      54,
      1944,
      16,
      64,
      64,
      1,
      4,
      1,
      9,
      36,
      1,
      6,
      "simulated",
      3.058819,
      false,
      false,
      0.0,
      36.0,
      "",
      "mla_cp_ring",
      0.077767789,
      0.0004732026,
      0.000101114,
      0.0157140672,
      0.00065886,
      0.00166632,
      0.0007281685,
      0.000375363,
      0.0,
      0.0835215514,
      0.0,
      "attnGPU_b16 ffnGPU_b64 total_b64 g36 pp1 a(d/t/e/c)=4/1/1/9 f(d/t/e)=1/1/36 mtp_s6 prefill=off decode36:attnGPU_b16",
      "MTP=on PD=off AF=off",
      "decode g=36 attnGPU_b=16 pp=1 attn dp/tp/ep/cp=4/1/1/9 ffn dp/tp/ep=1/1/36",
      "prefill off"
    ],
    [
      "H200_36_decode_batch16_I400000_O32768",
      "HGX-H200",
      36,
      "mtp",
      116094333.64,
      116.09433364,
      28,
      49,
      1764,
      16,
      64,
      64,
      1,
      4,
      1,
      9,
      36,
      1,
      7,
      "simulated",
      3.1411733,
      false,
      false,
      0.0,
      36.0,
      "",
      "mla_cp_ring",
      0.077945486,
      0.0004732026,
      0.000113612,
      0.0179160768,
      0.00073968,
      0.00114816,
      0.0007893355,
      0.000375367,
      0.0,
      0.0950349158,
      0.0,
      "attnGPU_b16 ffnGPU_b64 total_b64 g36 pp1 a(d/t/e/c)=4/1/1/9 f(d/t/e)=1/1/36 mtp_s7 prefill=off decode36:attnGPU_b16",
      "MTP=on PD=off AF=off",
      "decode g=36 attnGPU_b=16 pp=1 attn dp/tp/ep/cp=4/1/1/9 ffn dp/tp/ep=1/1/36",
      "prefill off"
    ],
    [
      "H200_36_decode_batch16_I400000_O32768",
      "HGX-H200",
      36,
      "mtp",
      179104508.98064515,
      179.1045089806,
      18,
      32,
      1152,
      16,
      64,
      64,
      1,
      4,
      1,
      9,
      36,
      1,
      8,
      "simulated",
      3.19882131,
      false,
      false,
      0.0,
      36.0,
      "",
      "mla_compute",
      0.154907626,
      0.0004732026,
      0.000119104,
      0.0201180864,
      0.00079422,
      0.00114816,
      0.0008505024,
      0.000504066,
      0.0,
      0.1065482803,
      0.0,
      "attnGPU_b16 ffnGPU_b64 total_b64 g36 pp1 a(d/t/e/c)=4/1/1/9 f(d/t/e)=1/1/36 mtp_s8 prefill=off decode36:attnGPU_b16",
      "MTP=on PD=off AF=off",
      "decode g=36 attnGPU_b=16 pp=1 attn dp/tp/ep/cp=4/1/1/9 ffn dp/tp/ep=1/1/36",
      "prefill off"
    ],
    [
      "H200_36_decode_batch16_I400000_O32768",
      "HGX-H200",
      36,
      "mtp",
      181783960.58064517,
      181.7839605806,
      18,
      32,
      1152,
      16,
      64,
      64,
      1,
      4,
      1,
      9,
      36,
      1,
      9,
      "simulated",
      3.239174917,
      false,
      false,
      0.0,
      36.0,
      "",
      "mla_compute",
      0.155010108,
      0.0004732026,
      0.000132338,
      0.022320096,
      0.00088242,
      0.00114816,
      0.0009116693,
      0.000504068,
      0.0,
      0.1180616448,
      0.0,
      "attnGPU_b16 ffnGPU_b64 total_b64 g36 pp1 a(d/t/e/c)=4/1/1/9 f(d/t/e)=1/1/36 mtp_s9 prefill=off decode36:attnGPU_b16",
      "MTP=on PD=off AF=off",
      "decode g=36 attnGPU_b=16 pp=1 attn dp/tp/ep/cp=4/1/1/9 ffn dp/tp/ep=1/1/36",
      "prefill off"
    ],
    [
      "H200_36_decode_batch16_I400000_O32768",
      "HGX-H200",
      36,
      "mtp",
      33780534.55344263,
      33.7805345534,
      51,
      90,
      3240,
      16,
      64,
      64,
      1,
      4,
      1,
      9,
      18,
      2,
      1,
      "simulated",
      1.7,
      false,
      false,
      0.0,
      36.0,
      "",
      "mla_cp_ring",
      0.019999932,
      0.0004732026,
      4.1654e-05,
      0.0047040192,
      0.0002778,
      0.0030534,
      0.0005446677,
      0.000278824,
      0.0,
      0.025954729,
      0.001567476,
      "attnGPU_b16 ffnGPU_b64 total_b64 g36 pp1 a(d/t/e/c)=4/1/1/9 f(d/t/e)=1/2/18 mtp_s1 prefill=off decode36:attnGPU_b16",
      "MTP=on PD=off AF=off",
      "decode g=36 attnGPU_b=16 pp=1 attn dp/tp/ep/cp=4/1/1/9 ffn dp/tp/ep=1/2/18",
      "prefill off"
    ],
    [
      "H200_36_decode_batch16_I400000_O32768",
      "HGX-H200",
      36,
      "mtp",
      47844075.633442625,
      47.8440756334,
      46,
      82,
      2952,
      16,
      64,
      64,
      1,
      4,
      1,
      9,
      18,
      2,
      2,
      "simulated",
      2.19,
      false,
      false,
      0.0,
      36.0,
      "",
      "mla_cp_ring",
      0.032031498,
      0.0004732026,
      4.167e-05,
      0.0069060288,
      0.00027804,
      0.00305364,
      0.0006670016,
      0.000298131,
      0.0,
      0.0374680934,
      0.001623474,
      "attnGPU_b16 ffnGPU_b64 total_b64 g36 pp1 a(d/t/e/c)=4/1/1/9 f(d/t/e)=1/2/18 mtp_s2 prefill=off decode36:attnGPU_b16",
      "MTP=on PD=off AF=off",
      "decode g=36 attnGPU_b=16 pp=1 attn dp/tp/ep/cp=4/1/1/9 ffn dp/tp/ep=1/2/18",
      "prefill off"
    ],
    [
      "H200_36_decode_batch16_I400000_O32768",
      "HGX-H200",
      36,
      "mtp",
      61902716.2052459,
      61.9027162052,
      41,
      73,
      2628,
      16,
      64,
      64,
      1,
      4,
      1,
      9,
      18,
      2,
      3,
      "simulated",
      2.533,
      false,
      false,
      0.0,
      36.0,
      "",
      "mla_cp_ring",
      0.039254686,
      0.0004732026,
      4.1686e-05,
      0.0091080384,
      0.00027804,
      0.00222096,
      0.0007893355,
      0.000311005,
      0.0,
      0.0489814579,
      0.001681272,
      "attnGPU_b16 ffnGPU_b64 total_b64 g36 pp1 a(d/t/e/c)=4/1/1/9 f(d/t/e)=1/2/18 mtp_s3 prefill=off decode36:attnGPU_b16",
      "MTP=on PD=off AF=off",
      "decode g=36 attnGPU_b=16 pp=1 attn dp/tp/ep/cp=4/1/1/9 ffn dp/tp/ep=1/2/18",
      "prefill off"
    ],
    [
      "H200_36_decode_batch16_I400000_O32768",
      "HGX-H200",
      36,
      "mtp",
      75970202.74426231,
      75.9702027443,
      37,
      65,
      2340,
      16,
      64,
      64,
      1,
      4,
      1,
      9,
      18,
      2,
      4,
      "simulated",
      2.7731,
      false,
      false,
      0.0,
      36.0,
      "",
      "mla_cp_ring",
      0.05369215,
      0.0004732026,
      4.1702e-05,
      0.011310048,
      0.00027828,
      0.00166608,
      0.0009116693,
      0.000332725,
      0.0,
      0.0604948224,
      0.001738828,
      "attnGPU_b16 ffnGPU_b64 total_b64 g36 pp1 a(d/t/e/c)=4/1/1/9 f(d/t/e)=1/2/18 mtp_s4 prefill=off decode36:attnGPU_b16",
      "MTP=on PD=off AF=off",
      "decode g=36 attnGPU_b=16 pp=1 attn dp/tp/ep/cp=4/1/1/9 ffn dp/tp/ep=1/2/18",
      "prefill off"
    ],
    [
      "H200_36_decode_batch16_I400000_O32768",
      "HGX-H200",
      36,
      "mtp",
      96274508.52490745,
      96.2745085249,
      31,
      55,
      1980,
      16,
      64,
      64,
      1,
      4,
      1,
      9,
      18,
      2,
      5,
      "simulated",
      2.94117,
      false,
      false,
      0.0,
      36.0,
      "",
      "mla_compute",
      0.077748938,
      0.0004732026,
      4.1718e-05,
      0.0135120576,
      0.000282,
      0.00166608,
      0.0010340032,
      0.000375361,
      0.0,
      0.0720081869,
      0.001794826,
      "attnGPU_b16 ffnGPU_b64 total_b64 g36 pp1 a(d/t/e/c)=4/1/1/9 f(d/t/e)=1/2/18 mtp_s5 prefill=off decode36:attnGPU_b16",
      "MTP=on PD=off AF=off",
      "decode g=36 attnGPU_b=16 pp=1 attn dp/tp/ep/cp=4/1/1/9 ffn dp/tp/ep=1/2/18",
      "prefill off"
    ],
    [
      "H200_36_decode_batch16_I400000_O32768",
      "HGX-H200",
      36,
      "mtp",
      104159362.3632787,
      104.1593623633,
      30,
      53,
      1908,
      16,
      64,
      64,
      1,
      4,
      1,
      9,
      18,
      2,
      6,
      "simulated",
      3.058819,
      false,
      false,
      0.0,
      36.0,
      "",
      "mla_cp_ring",
      0.077767789,
      0.0004732026,
      5.0613e-05,
      0.0157140672,
      0.00032628,
      0.00140136,
      0.0011563371,
      0.000375363,
      0.0,
      0.0835215514,
      0.001852504,
      "attnGPU_b16 ffnGPU_b64 total_b64 g36 pp1 a(d/t/e/c)=4/1/1/9 f(d/t/e)=1/2/18 mtp_s6 prefill=off decode36:attnGPU_b16",
      "MTP=on PD=off AF=off",
      "decode g=36 attnGPU_b=16 pp=1 attn dp/tp/ep/cp=4/1/1/9 ffn dp/tp/ep=1/2/18",
      "prefill off"
    ],
    [
      "H200_36_decode_batch16_I400000_O32768",
      "HGX-H200",
      36,
      "mtp",
      118326752.93508196,
      118.3267529351,
      27,
      48,
      1728,
      16,
      64,
      64,
      1,
      4,
      1,
      9,
      18,
      2,
      7,
      "simulated",
      3.1411733,
      false,
      false,
      0.0,
      36.0,
      "",
      "mla_cp_ring",
      0.077945486,
      0.0004732026,
      5.6869e-05,
      0.0179160768,
      0.00044166,
      0.00116088,
      0.0012786709,
      0.000375367,
      0.0,
      0.0950349158,
      0.001910302,
      "attnGPU_b16 ffnGPU_b64 total_b64 g36 pp1 a(d/t/e/c)=4/1/1/9 f(d/t/e)=1/2/18 mtp_s7 prefill=off decode36:attnGPU_b16",
      "MTP=on PD=off AF=off",
      "decode g=36 attnGPU_b=16 pp=1 attn dp/tp/ep/cp=4/1/1/9 ffn dp/tp/ep=1/2/18",
      "prefill off"
    ],
    [
      "H200_36_decode_batch16_I400000_O32768",
      "HGX-H200",
      36,
      "mtp",
      181378701.27572715,
      181.3787012757,
      18,
      32,
      1152,
      16,
      64,
      64,
      1,
      4,
      1,
      9,
      18,
      2,
      8,
      "simulated",
      3.19882131,
      false,
      false,
      0.0,
      36.0,
      "",
      "mla_compute",
      0.154907626,
      0.0004732026,
      5.9614e-05,
      0.0201180864,
      0.00048576,
      0.00116088,
      0.0014010048,
      0.000504066,
      0.0,
      0.1065482803,
      0.001966178,
      "attnGPU_b16 ffnGPU_b64 total_b64 g36 pp1 a(d/t/e/c)=4/1/1/9 f(d/t/e)=1/2/18 mtp_s8 prefill=off decode36:attnGPU_b16",
      "MTP=on PD=off AF=off",
      "decode g=36 attnGPU_b=16 pp=1 attn dp/tp/ep/cp=4/1/1/9 ffn dp/tp/ep=1/2/18",
      "prefill off"
    ],
    [
      "H200_36_decode_batch16_I400000_O32768",
      "HGX-H200",
      36,
      "mtp",
      184078816.3347435,
      184.0788163347,
      18,
      32,
      1152,
      16,
      64,
      64,
      1,
      4,
      1,
      9,
      18,
      2,
      9,
      "simulated",
      3.239174917,
      false,
      false,
      0.0,
      36.0,
      "",
      "mla_compute",
      0.155010108,
      0.0004732026,
      6.6239e-05,
      0.022320096,
      0.0005445,
      0.00116088,
      0.0015233387,
      0.000504068,
      0.0,
      0.1180616448,
      0.002023856,
      "attnGPU_b16 ffnGPU_b64 total_b64 g36 pp1 a(d/t/e/c)=4/1/1/9 f(d/t/e)=1/2/18 mtp_s9 prefill=off decode36:attnGPU_b16",
      "MTP=on PD=off AF=off",
      "decode g=36 attnGPU_b=16 pp=1 attn dp/tp/ep/cp=4/1/1/9 ffn dp/tp/ep=1/2/18",
      "prefill off"
    ]
  ],
  "frontier_rows": [
    [
      "H200_36_decode_batch16_I400000_O32768",
      "HGX-H200",
      36,
      null,
      29615922.277419355,
      29.6159222774,
      34,
      136,
      4896,
      16,
      144,
      144,
      1,
      9,
      1,
      4,
      36,
      1,
      0,
      "simulated_baseline",
      1.0,
      null,
      null,
      null,
      null,
      null,
      "mla_compute",
      0.022395548,
      0.0010644697,
      8.3276e-05,
      0.0052545216,
      0.00055536,
      0.00333096,
      0.0004376256,
      0.000262737,
      0.0,
      0.0013378618,
      0.0,
      "attnGPU_b16 ffnGPU_b144 total_b144 g36 pp1 a(d/t/e/c)=9/1/1/4 f(d/t/e)=1/1/36 mtp_s0 decode36:attnGPU_b16",
      "MTP=off PD=off AF=off",
      "decode g=36 attnGPU_b=16 pp=1 attn dp/tp/ep/cp=9/1/1/4 ffn dp/tp/ep=1/1/36",
      "prefill off"
    ],
    [
      "H200_36_decode_batch16_I400000_O32768",
      "HGX-H200",
      36,
      "mtp",
      31849740.16,
      31.84974016,
      54,
      95,
      3420,
      16,
      64,
      64,
      1,
      4,
      1,
      9,
      36,
      1,
      1,
      "simulated",
      1.7,
      false,
      false,
      0.0,
      36.0,
      "",
      "mla_cp_ring",
      0.019999932,
      0.0004732026,
      8.3276e-05,
      0.0047040192,
      0.00055536,
      0.00333096,
      0.0004223339,
      0.000278824,
      0.0,
      0.025954729,
      0.0,
      "attnGPU_b16 ffnGPU_b64 total_b64 g36 pp1 a(d/t/e/c)=4/1/1/9 f(d/t/e)=1/1/36 mtp_s1 prefill=off decode36:attnGPU_b16",
      "MTP=on PD=off AF=off",
      "decode g=36 attnGPU_b=16 pp=1 attn dp/tp/ep/cp=4/1/1/9 ffn dp/tp/ep=1/1/36",
      "prefill off"
    ]
  ],
  "frontier_deltas": [
    {
      "frontier_order": 1,
      "changed_parameters": "frontier start",
      "frontier_label": "attnGPU_b16 ffnGPU_b144 total_b144 g36 pp1 a(d/t/e/c)=9/1/1/4 f(d/t/e)=1/1/36 mtp_s0 decode36:attnGPU_b16",
      "delta_tps_per_user": null,
      "delta_tps_per_gpu": null,
      "delta_total_throughput": null
    },
    {
      "frontier_order": 2,
      "changed_parameters": "strategy: nan -> mtp; batch ffn/gpu: 144 -> 64; total machine batch: 144 -> 64; attn dp: 9 -> 4; attn cp: 4 -> 9; mtp stage: 0 -> 1; pd: nan -> off; af: nan -> off; prefill gpu: nan -> 0; decode gpu: nan -> 36",
      "frontier_label": "strategy: nan -> mtp; batch ffn/gpu: 144 -> 64; total machine batch: 144 -> 64; attn dp: 9 -> 4; attn cp: 4 -> 9; mtp stage: 0 -> 1; pd: nan -> off; af: nan -> off; prefill gpu: nan -> 0; decode gpu: nan -> 36",
      "delta_tps_per_user": 20,
      "delta_tps_per_gpu": -41,
      "delta_total_throughput": -1476
    }
  ],
  "frontiers_by_gpu": {
    "36": {
      "summary": {
        "gpu_num": 36,
        "point_count": 60,
        "frontier_count": 2,
        "x_metric": "tps_per_user",
        "y_metric": "throughput_total_tps",
        "best_tps_per_user": 54,
        "best_y_metric": 4896,
        "best_tps_per_gpu": 136,
        "best_throughput_total_tps": 4896
      },
      "frontier_rows": [
        [
          "H200_36_decode_batch16_I400000_O32768",
          "HGX-H200",
          36,
          null,
          29615922.277419355,
          29.6159222774,
          34,
          136,
          4896,
          16,
          144,
          144,
          1,
          9,
          1,
          4,
          36,
          1,
          0,
          "simulated_baseline",
          1.0,
          null,
          null,
          null,
          null,
          null,
          "mla_compute",
          0.022395548,
          0.0010644697,
          8.3276e-05,
          0.0052545216,
          0.00055536,
          0.00333096,
          0.0004376256,
          0.000262737,
          0.0,
          0.0013378618,
          0.0,
          "attnGPU_b16 ffnGPU_b144 total_b144 g36 pp1 a(d/t/e/c)=9/1/1/4 f(d/t/e)=1/1/36 mtp_s0 decode36:attnGPU_b16",
          "MTP=off PD=off AF=off",
          "decode g=36 attnGPU_b=16 pp=1 attn dp/tp/ep/cp=9/1/1/4 ffn dp/tp/ep=1/1/36",
          "prefill off"
        ],
        [
          "H200_36_decode_batch16_I400000_O32768",
          "HGX-H200",
          36,
          "mtp",
          31849740.16,
          31.84974016,
          54,
          95,
          3420,
          16,
          64,
          64,
          1,
          4,
          1,
          9,
          36,
          1,
          1,
          "simulated",
          1.7,
          false,
          false,
          0.0,
          36.0,
          "",
          "mla_cp_ring",
          0.019999932,
          0.0004732026,
          8.3276e-05,
          0.0047040192,
          0.00055536,
          0.00333096,
          0.0004223339,
          0.000278824,
          0.0,
          0.025954729,
          0.0,
          "attnGPU_b16 ffnGPU_b64 total_b64 g36 pp1 a(d/t/e/c)=4/1/1/9 f(d/t/e)=1/1/36 mtp_s1 prefill=off decode36:attnGPU_b16",
          "MTP=on PD=off AF=off",
          "decode g=36 attnGPU_b=16 pp=1 attn dp/tp/ep/cp=4/1/1/9 ffn dp/tp/ep=1/1/36",
          "prefill off"
        ]
      ],
      "frontier_deltas": [
        {
          "frontier_order": 1,
          "changed_parameters": "frontier start",
          "frontier_label": "attnGPU_b16 ffnGPU_b144 total_b144 g36 pp1 a(d/t/e/c)=9/1/1/4 f(d/t/e)=1/1/36 mtp_s0 decode36:attnGPU_b16",
          "delta_tps_per_user": null,
          "delta_tps_per_gpu": null,
          "delta_total_throughput": null
        },
        {
          "frontier_order": 2,
          "changed_parameters": "strategy: nan -> mtp; batch ffn/gpu: 144 -> 64; total machine batch: 144 -> 64; attn dp: 9 -> 4; attn cp: 4 -> 9; mtp stage: 0 -> 1; pd: nan -> off; af: nan -> off; prefill gpu: nan -> 0; decode gpu: nan -> 36",
          "frontier_label": "strategy: nan -> mtp; batch ffn/gpu: 144 -> 64; total machine batch: 144 -> 64; attn dp: 9 -> 4; attn cp: 4 -> 9; mtp stage: 0 -> 1; pd: nan -> off; af: nan -> off; prefill gpu: nan -> 0; decode gpu: nan -> 36",
          "delta_tps_per_user": 20,
          "delta_tps_per_gpu": -41,
          "delta_total_throughput": -1476
        }
      ]
    }
  }
}
